corregraphe/__init__.py
corregraphe/core.py
corregraphe-0.1.1.dist-info/LICENSE
corregraphe-0.1.1.dist-info/METADATA
corregraphe-0.1.1.dist-info/WHEEL
corregraphe-0.1.1.dist-info/top_level.txt
corregraphe-0.1.1.dist-info/RECORD
