Metadata-Version: 2.1
Name: corregraphe
Version: 0.1.1
Summary: Correlation graphs with NetworkX
Home-page: https://github.com/theodcr/corregraphe
Author: "Théo Delecour"
Author-email: "theo.delecour@gmail.com"
License: MIT
Platform: UNKNOWN
Classifier: License :: OSI Approved :: MIT License
Classifier: Programming Language :: Python :: 3.6
Classifier: Programming Language :: Python :: 3.7
Requires-Python: >= 3.6
Requires-Dist: hvplot
Requires-Dist: networkx
Requires-Dist: pandas
Requires-Dist: scipy
Provides-Extra: dev
Requires-Dist: black ; extra == 'dev'
Requires-Dist: flake8 ; extra == 'dev'
Requires-Dist: isort ; extra == 'dev'
Requires-Dist: mypy ; extra == 'dev'
